nexussim/__init__.py
nexussim/analysis.py
nexussim/core.py
nexussim-0.1.1.dist-info/licenses/LICENSE.txt
nexussim-0.1.1.dist-info/METADATA
nexussim-0.1.1.dist-info/WHEEL
nexussim-0.1.1.dist-info/top_level.txt
nexussim-0.1.1.dist-info/RECORD
