Metadata-Version: 2.4
Name: nexussim
Version: 0.1.1
Summary: A framework for agent-based modeling of dynamic spatial processes.
Author-email: "Matthew R. Marcelino" <matthew.marcelino@uvm.edu>
License: CC-BY-NC-SA-4.0
Project-URL: Homepage, https://github.com/mrmarcelino/nexussim
Project-URL: Issues, https://github.com/mrmarcelino/nexussim/issues
Classifier: Programming Language :: Python :: 3
Classifier: License :: Free for non-commercial use
Classifier: Operating System :: OS Independent
Classifier: Intended Audience :: Science/Research
Classifier: Topic :: Scientific/Engineering
Requires-Python: >=3.8
License-File: LICENSE.txt
Requires-Dist: numpy
Requires-Dist: pandas
Requires-Dist: rasterio
Requires-Dist: matplotlib
Requires-Dist: scikit-image
Requires-Dist: imageio
Requires-Dist: scipy
Dynamic: license-file
